{
  "AWSTemplateFormatVersion": "2010-09-09",

  "Description": "OpsWorks stack containing all instances",

  "Parameters": {
    "vpcId": {
      "Type": "AWS::EC2::VPC::Id"
    },
    "bucketName": {
      "Type": "String"
    },
    "keyName": {
      "Type": "AWS::EC2::KeyPair::KeyName"
    },
    "availabilityZone": {
      "Type": "String"
    },
    "subnetId": {
      "Type": "AWS::EC2::Subnet::Id"
    },
    "crowdHostName": {
      "Type": "String"
    },
    "crowdPort": {
      "Type": "String"
    },
    "jiraHostName": {
      "Type": "String"
    },
    "jiraPort": {
      "Type": "String"
    },
    "confluenceHostName": {
      "Type": "String"
    },
    "confluencePort": {
      "Type": "String"
    },
    "stashHostName": {
      "Type": "String"
    },
    "stashPort": {
      "Type": "String"
    },
    "bambooHostName": {
      "Type": "String"
    },
    "bambooPort": {
      "Type": "String"
    },
    "s3AccessKeyId": {
      "Type": "String"
    },
    "s3SecretAccessKey": {
      "Type": "String"
    }
  },

  "Mappings": {
  },

  "Conditions": {
  },

  "Resources": {

    "stack": {
      "Type": "AWS::OpsWorks::Stack",
      "Properties": {
        "ConfigurationManager": {
          "Name": "Chef",
          "Version": "11.10"
        },
        "CustomCookbooksSource": {
          "Password": { "Ref": "s3SecretAccessKey" },
          "Username": { "Ref": "s3AccessKeyId" },
          "Type": "s3",
          "Url": { "Fn::Join": [ "", [ "https://s3.amazonaws.com/", { "Ref": "bucketName" }, "/cookbooks.tar.gz" ] ] }
        },
        "CustomJson": {
          "nginx": {
            "crowd": {
              "host": { "Ref": "crowdHostName" },
              "port": { "Ref": "crowdPort" }
            },
            "jira": {
              "host": { "Ref": "jiraHostName" },
              "port": { "Ref": "jiraPort" }
            },
            "confluence": {
              "host": { "Ref": "confluenceHostName" },
              "port": { "Ref": "confluencePort" }
            },
            "stash": {
              "host": { "Ref": "stashHostName" },
              "port": { "Ref": "stashPort" }
            },
            "bamboo": {
              "host": { "Ref": "bambooHostName" },
              "port": { "Ref": "bambooPort" }
            }
          }
        },
        "ServiceRoleArn" : { "Fn::Join": ["", ["arn:aws:iam::", {"Ref":"AWS::AccountId"}, ":role/aws-opsworks-service-role"]] },
        "DefaultInstanceProfileArn" : { "Fn::Join": ["", ["arn:aws:iam::", {"Ref":"AWS::AccountId"}, ":instance-profile/aws-opsworks-ec2-role"]] },
        "DefaultAvailabilityZone": { "Ref": "availabilityZone" },
        "DefaultOs": "Ubuntu 14.04 LTS",
        "DefaultRootDeviceType": "ebs",
        "DefaultSshKeyName": { "Ref": "keyName" },
        "DefaultSubnetId": { "Ref": "subnetId" },
        "HostnameTheme": "Baked_Goods",
        "Name": "atlassian-test",
        "UseCustomCookbooks": true,
        "UseOpsworksSecurityGroups": true,
        "VpcId": { "Ref": "vpcId" }
      }
    }

  },

  "Outputs": {
    "stackId": {
      "Value": { "Ref": "stack" }
    }
  }
}
